{" ": 29, "(": 68, ",": 10, "0": 22, "4": 26, "8": 61, "<": 44, "D": 47, "H": 75, "L": 55, "P": 28, "T": 37, "X": 85, "\\": 43, "d": 12, "h": 13, "l": 11, "p": 20, "t": 3, "x": 72, "#": 71, "'": 39, "+": 87, "/": 19, "3": 34, "7": 59, ";": 33, "?": 80, "C": 27, "G": 70, "K": 78, "O": 41, "S": 50, "W": 76, "[": 83, "_": 60, "c": 18, "g": 25, "k": 36, "o": 6, "s": 9, "w": 35, "{": 16, "\"": 1, "&": 31, "*": 79, ".": 69, "2": 30, "6": 57, ":": 4, ">": 45, "B": 51, "F": 77, "J": 81, "N": 58, "R": 42, "V": 82, "b": 53, "f": 46, "j": 64, "n": 21, "r": 7, "v": 49, "z": 54, "!": 65, ")": 74, "-": 56, "1": 32, "5": 62, "9": 66, "=": 38, "A": 48, "E": 40, "I": 67, "M": 52, "Q": 86, "U": 73, "Y": 63, "]": 84, "a": 5, "e": 2, "i": 24, "m": 23, "q": 15, "u": 8, "y": 14, "}": 17}